{
  "employees": [
    {
      "first": "Adam",
      "last": "",
      "email": "",
      "phone": "",
      "birth": "",
      "dept": "HR",
      "super": true,
      "id": 72
    },
    {
      "first": "Adam",
      "last": "",
      "email": "",
      "phone": "",
      "birth": "",
      "dept": "HR",
      "super": true,
      "gender": "Male",
      "id": 73
    },
    {
      "first": "Adam",
      "last": "",
      "email": "",
      "phone": "",
      "birth": "",
      "dept": "HR",
      "super": true,
      "id": 74
    },
    {
      "first": "Adam",
      "last": "",
      "email": "",
      "phone": "",
      "birth": "",
      "dept": "HR",
      "super": true,
      "id": 75
    },
    {
      "first": "Adam",
      "last": "",
      "email": "",
      "phone": "",
      "birth": "",
      "dept": "HR",
      "super": true,
      "id": 76
    },
    {
      "first": "Adam",
      "last": "Bowen",
      "email": "akwdunawudnw",
      "phone": "818617175",
      "birth": "1818771",
      "dept": "HR",
      "super": true,
      "gender": "Male",
      "id": 77
    }
  ]
}